setup.cfg
setup.py
nimoy/__init__.py
nimoy/connection.py
nimoy/exceptions.py
nimoy/hexadapter.py
nimoy/schemas.py
nimoy/utils.py
nimoy/version.py
nimoy.egg-info/PKG-INFO
nimoy.egg-info/SOURCES.txt
nimoy.egg-info/dependency_links.txt
nimoy.egg-info/not-zip-safe
nimoy.egg-info/top_level.txt
nimoy/backends/__init__.py
nimoy/backends/base.py
nimoy/backends/dynamodb.py
nimoy/backends/es.py
nimoy/backends/in_memory.py
nimoy/fields/__init__.py
nimoy/fields/composite.py
nimoy/fields/scalar.py