Metadata-Version: 1.1
Name: nimoy
Version: 0.8.3
Summary: Python3 Database Access Layer with Simple Functions and Dictionaries
Home-page: https://github.com/laco/python-nimoy/
Author: László Andrási
Author-email: mail@laszloandrasi.com
License: Apache2.0
Download-URL: https://github.com/laco/python-nimoy/tarball/0.8.3
Platform: any
Classifier: Development Status :: 4 - Beta
Classifier: Environment :: Web Environment
Classifier: Intended Audience :: Developers
Classifier: License :: OSI Approved :: BSD License
Classifier: Operating System :: OS Independent
Classifier: Programming Language :: Python
Classifier: Programming Language :: Python :: 3
Classifier: Topic :: Software Development :: Libraries :: Python Modules
